binance4py/__init__.py
binance4py/api.py
binance4py/client.py
binance4py/endpoints.py
binance4py/exception.py
binance4py/py.typed
binance4py/resources/__init__.py
binance4py/resources/base.py
binance4py/resources/general.py
binance4py/resources/market.py
binance4py/resources/spot.py
binance4py/typing.py
binance4py/utils.py
binance4py/websocket.py
binance4py-1.0.2.dist-info/LICENSE
binance4py-1.0.2.dist-info/WHEEL
binance4py-1.0.2.dist-info/METADATA
binance4py-1.0.2.dist-info/RECORD
