Metadata-Version: 2.1
Name: binance4py
Version: 1.0.2
Summary: Python binance API wrapper
Home-page: https://github.com/ren3104/binance4py
License: MIT
Keywords: python,binance4py,api,websocket,cryptocurrency,crypto,exchange,trade,trading,binance,bitcoin,btc,ethereum,eth
Author: ren3104
Author-email: 2ren3104@gmail.com
Requires-Python: >=3.7,<4.0
Classifier: Intended Audience :: Developers
Classifier: Intended Audience :: Financial and Insurance Industry
Classifier: Intended Audience :: Information Technology
Classifier: License :: OSI Approved :: MIT License
Classifier: Operating System :: OS Independent
Classifier: Programming Language :: Python :: 3
Classifier: Programming Language :: Python :: 3.10
Classifier: Programming Language :: Python :: 3.7
Classifier: Programming Language :: Python :: 3.8
Classifier: Programming Language :: Python :: 3.9
Classifier: Topic :: Office/Business :: Financial :: Investment
Classifier: Topic :: Software Development :: Libraries :: Python Modules
Classifier: Typing :: Typed
Requires-Dist: aiohttp (>=3.8.3,<4.0.0)
Project-URL: Bug Tracker, https://github.com/ren3104/binance4py/issues
Project-URL: Repository, https://github.com/ren3104/binance4py
